featureColByTorch-1.0.dist-info/METADATA
featureColByTorch-1.0.dist-info/RECORD
featureColByTorch-1.0.dist-info/WHEEL
featureColByTorch-1.0.dist-info/top_level.txt
transformers/CategoryTransformer.py
transformers/NumberTransformer.py
transformers/SequenceTransformer.py
transformers/__init__.py
transformers/base.py
transformers/columnFlow.py
