Metadata-Version: 2.1
Name: featureColByTorch
Version: 1.0
Summary: this is a feature column and transformer tools in pytorch, which is like the featureColumn class in Tensorflow
Home-page: https://blog.csdn.net/qq_40742298
Author: Braylon
Author-email: S.Braylon1002@gmail.com
Maintainer: Braylon
Maintainer-email: S.Braylon1002@gmail.com
License: BSD License
Platform: all
Requires-Dist: numpy
Requires-Dist: pandas
